cdpy/__init__.py
cdpy/browser.py
cdpy/chromium_downloader.py
cdpy/command.py
cdpy/connection.py
cdpy/coverage.py
cdpy/dialog.py
cdpy/element_handle.py
cdpy/emulation_manager.py
cdpy/errors.py
cdpy/execution_context.py
cdpy/frame_manager.py
cdpy/helper.py
cdpy/input.py
cdpy/launcher.py
cdpy/multimap.py
cdpy/navigator_watcher.py
cdpy/network_manager.py
cdpy/options.py
cdpy/page.py
cdpy/target.py
cdpy/tracing.py
cdpy/us_keyboard_layout.py
cdpy/util.py
cdpy/worker.py
cdpy-0.2.7.dist-info/WHEEL
cdpy-0.2.7.dist-info/entry_points.txt
cdpy-0.2.7.dist-info/METADATA
cdpy-0.2.7.dist-info/RECORD
