Metadata-Version: 2.3
Name: cdpy
Version: 0.2.7
Summary: Add your description here
Author: Dzmitry Sianiuk
Author-email: Dzmitry Sianiuk <dz.sianiuk@hey.com>
Requires-Dist: certifi>=2025.8.3
Requires-Dist: platformdirs>=4.4.0
Requires-Dist: pyee>=13.0.0
Requires-Dist: tqdm>=4.67.1
Requires-Dist: urllib3>=2.5.0
Requires-Dist: websockets>=15.0.1
Requires-Python: >=3.10
